{
  "stats": {
    "totalEnergy": { "value": "12,840", "unit": "kWh", "trend": "+12%", "trendType": "up" },
    "onlineRate": { "value": "98.2", "unit": "%", "trend": "+0.5%", "trendType": "up" },
    "pendingAlerts": { "value": "04", "unit": "项", "trend": "-2", "trendType": "down" },
    "carbonEmission": { "value": "842", "unit": "kg", "trend": "-4.2%", "trendType": "down" }
  },
  "energyChart": [
    { "name": "Mon", "value": 400 },
    { "name": "Tue", "value": 300 },
    { "name": "Wed", "value": 500 },
    { "name": "Thu", "value": 280 },
    { "name": "Fri", "value": 590 },
    { "name": "Sat", "value": 320 },
    { "name": "Sun", "value": 250 }
  ],
  "alerts": [
    { "id": "1a2b3c4d-5e6f-7a8b-9c0d-1e2f3a4b5c6d", "device": "中央空调 A1", "level": "high", "message": "能耗异常波动 (超出阈值 20%)", "time": "10:15:22", "status": "pending" },
    { "id": "2b3c4d5e-6f7a-8b9c-0d1e-2f3a4b5c6d7e", "device": "配电柜 B3", "level": "medium", "message": "电压不稳定告警", "time": "09:45:10", "status": "pending" },
    { "id": "3c4d5e6f-7a8b-9c0d-1e2f-3a4b5c6d7e8f", "device": "水泵 C1", "level": "low", "message": "例行维保提醒", "time": "08:00:00", "status": "resolved" },
    { "id": "4d5e6f7a-8b9c-0d1e-2f3a-4b5c6d7e8f9a", "device": "电梯 #4", "level": "high", "message": "传感器故障", "time": "11:20:05", "status": "pending" },
    { "id": "5e6f7a8b-9c0d-1e2f-3a4b-5c6d7e8f9a0b", "device": "照明控制系统", "level": "medium", "message": "通讯中断", "time": "10:55:30", "status": "pending" }
  ]
}
